{
  "main": {
    "id": "e4bafde3c68a6fb3",
    "type": "split",
    "children": [
      {
        "id": "3b430f81ccedb895",
        "type": "tabs",
        "children": [
          {
            "id": "e3c417ba36192439",
            "type": "leaf",
            "state": {
              "type": "markdown",
              "state": {
                "file": "Technical/DSA/Algo/Alogrithms MOC.md",
                "mode": "source",
                "source": false
              }
            }
          },
          {
            "id": "d66452b094646a9b",
            "type": "leaf",
            "state": {
              "type": "markdown",
              "state": {
                "file": "Technical/DSA/Algo/Graph/MST/Kruskal.md",
                "mode": "source",
                "source": false
              }
            }
          }
        ],
        "currentTab": 1
      }
    ],
    "direction": "vertical"
  },
  "left": {
    "id": "686f44fbab6746d4",
    "type": "split",
    "children": [
      {
        "id": "4bb57e58b8f80419",
        "type": "tabs",
        "dimension": 62.007168458781365,
        "children": [
          {
            "id": "c6d173446b8ea23c",
            "type": "leaf",
            "state": {
              "type": "file-explorer",
              "state": {
                "sortOrder": "alphabetical"
              }
            }
          },
          {
            "id": "87b3971a23f9da73",
            "type": "leaf",
            "state": {
              "type": "search",
              "state": {
                "query": "",
                "matchingCase": false,
                "explainSearch": false,
                "collapseAll": false,
                "extraContext": false,
                "sortOrder": "alphabetical"
              }
            }
          },
          {
            "id": "2c9f7d276f7c17c2",
            "type": "leaf",
            "state": {
              "type": "tag",
              "state": {
                "sortOrder": "frequency",
                "useHierarchy": true
              }
            }
          },
          {
            "id": "12647ddaae5d883c",
            "type": "leaf",
            "state": {
              "type": "bookmarks",
              "state": {}
            }
          }
        ]
      },
      {
        "id": "4291af2bb5f79574",
        "type": "tabs",
        "dimension": 37.992831541218635,
        "children": [
          {
            "id": "de9bbc59fe5a4b25",
            "type": "leaf",
            "state": {
              "type": "outline",
              "state": {
                "file": "Technical/DSA/Algo/Graph/MST/Kruskal.md"
              }
            }
          }
        ]
      }
    ],
    "direction": "horizontal",
    "width": 268.5
  },
  "right": {
    "id": "8cf2b2f99d2fd9eb",
    "type": "split",
    "children": [
      {
        "id": "aa73b7c38d889831",
        "type": "tabs",
        "children": [
          {
            "id": "7e94e118fbed72e4",
            "type": "leaf",
            "state": {
              "type": "calendar",
              "state": {}
            }
          },
          {
            "id": "60e18b1cd30fd04e",
            "type": "leaf",
            "state": {
              "type": "backlink",
              "state": {
                "file": "Technical/DSA/Algo/Graph/MST/Kruskal.md",
                "collapseAll": false,
                "extraContext": false,
                "sortOrder": "alphabetical",
                "showSearch": false,
                "searchQuery": "",
                "backlinkCollapsed": false,
                "unlinkedCollapsed": true
              }
            }
          },
          {
            "id": "8f660ea5fa464db9",
            "type": "leaf",
            "state": {
              "type": "outgoing-link",
              "state": {
                "file": "Technical/DSA/Algo/Graph/MST/Kruskal.md",
                "linksCollapsed": false,
                "unlinkedCollapsed": true
              }
            }
          },
          {
            "id": "f0730ee2735a8bac",
            "type": "leaf",
            "state": {
              "type": "Strange New Worlds",
              "state": {}
            }
          },
          {
            "id": "db64c28ca17e64c2",
            "type": "leaf",
            "state": {
              "type": "all-properties",
              "state": {
                "sortOrder": "frequency"
              }
            }
          },
          {
            "id": "0e8a4607fb8072c6",
            "type": "leaf",
            "state": {
              "type": "file-properties",
              "state": {
                "file": "Technical/DSA/Algo/Graph/MST/Kruskal.md"
              }
            }
          },
          {
            "id": "e84e85fa044f64a9",
            "type": "leaf",
            "state": {
              "type": "smart-connections-view",
              "state": {}
            }
          },
          {
            "id": "29e5a04f3c020ef2",
            "type": "leaf",
            "state": {
              "type": "smart-connections-chat-view",
              "state": {}
            }
          }
        ],
        "currentTab": 7
      }
    ],
    "direction": "horizontal",
    "width": 466.5
  },
  "left-ribbon": {
    "hiddenItems": {
      "table-editor-obsidian:Advanced Tables Toolbar": false,
      "switcher:Open quick switcher": false,
      "canvas:Create new canvas": false,
      "daily-notes:Open today's daily note": false,
      "templates:Insert template": false,
      "command-palette:Open command palette": false,
      "graph:Open graph view": false,
      "obsidian-excalidraw-plugin:Create new drawing": false,
      "templater-obsidian:Templater": false,
      "obsidian-textgenerator-plugin:Generate Text!": false,
      "obsidian-textgenerator-plugin:Text Generator: Templates Packages Manager": false,
      "obsidian42-brat:BRAT": false,
      "dbfolder:Create a new database table": false,
      "homepage:Open homepage": false,
      "omnisearch:Omnisearch": false,
      "mermaid-tools:Open Mermaid Toolbar": false
    }
  },
  "active": "d66452b094646a9b",
  "lastOpenFiles": [
    "Technical/DSA/DS/Tree/DSU/Disjoint Set Union.md",
    "Technical/DSA/Algo/Graph/MST/Kruskal.md",
    "Technical/DSA/Algo/Graph/Traversal/BFS.md",
    "Technical/DSA/Algo/Graph/Traversal/DFS.md",
    "Technical/DSA/Algo/Base/Sorting/Merge Sort.md",
    "Technical/DSA/Algo/Base/Sorting/Heap Sort.md",
    "Technical/DSA/Algo/Base/Sorting/Bucket Sort.md",
    "Technical/DSA/Algo/Search/Binary Search/Binary Search Part 1.md",
    "Technical/DSA/Algo/Graph/Traversal/Topological Sorting.md",
    "Technical/DSA/Algo/Alogrithms MOC.md",
    "Technical/DSA/Algo/Graph/MST/Prim.md",
    "Technical/DSA/DSA MOC.md",
    "Technical/DSA/Algo/Base/Sorting/Bubble Sort.md",
    "Technical/DSA/Algo/Base/Recursion/Recursion.md",
    "Technical/DSA/Algo/Graph/MST/MST Problems.md",
    "Technical/DSA/Algo/Graph/SP/Dijkstra.md",
    "Technical/DSA/Algo/Graph/SP/Shortest Path.md",
    "Technical/DSA/Algo/Graph/MST/Minimum Spanning Tree.md",
    "Technical/DSA/Algo/Graph/SP",
    "Technical/DSA/Algo/Graph/Graph MOC.md",
    "Technical/DSA/DS/Queue/Priority/Priority Queue.md",
    "Technical/DSA/DS/Data Structures MOC.md",
    "Technical/DSA/Thinking",
    "Technical/DSA/Algo/Search/Binary Search/Binary Search Part 2.md",
    "Technical/DSA/Algo/Search/Backtracking/Backtracking Problems.md",
    "Technical/DSA/Algo/Search/Backtracking/Branch and Bound.md",
    "Technical/DSA/DS/Heap/Top-K Problem.md",
    "Technical/DSA/Algo/Search",
    "Technical/DSA/DS/Heap/Heap.md",
    "Technical/DSA/DS/Heap",
    "Technical/DSA/Algo/DP/Digit",
    "Technical/DSA/Algo/DP/Counting",
    "Technical/DSA/Algo/DP/State",
    "Technical/DSA/Algo/Base",
    "Technical/DSA/Algo/DP/Interval",
    "Technical/DSA/Algo/DP/Knapsack",
    "Extras/Media/20220509113955.png",
    "Extras/Media/20220509094655.png",
    "Extras/Media/20220509094635.png",
    "Extras/Media/20220507174723.png",
    "Extras/Media/20220507172300.png",
    "Extras/Media/20220507142647.png",
    "Extras/Media/20220507112934.png",
    "Extras/Media/20220505145302.png",
    "Extras/Media/20220505145234.png",
    "Extras/Media/20220317163249.png"
  ]
}